[
  {
    "Events": [
      {
        "Name": "Appuyer sur",
        "Function": "Game.keys.* == True",
        "Description": "l\u0027utilisateur appuie sur la touche d\u00E9sign\u00E9e",
        "Available_parameter_values": null,
        "Parameter_value": "ESPACE",
        "Parameter_count": 1,
        "Show_list": "Visible",
        "Show_number": "Collapsed",
        "Parameter_type": "string"
      }
    ],
    "Image": "C:\\Users\\user\\Documents\\COURS\\C#\\Projet\\bricks-studio\\assets\\lego_bleu.png",
    "Name": "espace",
    "id": "6243ba37-1862-4ad8-b4c2-7c4d7f61e6ae",
    "margin": {
      "Left": 249.66666666666663,
      "Top": 360.66666666666663,
      "Right": 0,
      "Bottom": 0
    },
    "x": 249.66666666666663,
    "y": 360.66666666666663,
    "width": 70,
    "height": 35
  }
]